hc_pyconsul/__init__.py
hc_pyconsul/exceptions.py
hc_pyconsul/helpers/__init__.py
hc_pyconsul/helpers/services.py
hc_pyconsul/lib/__init__.py
hc_pyconsul/lib/catalog.py
hc_pyconsul/lib/consul.py
hc_pyconsul/lib/health.py
hc_pyconsul/lib/tracing.py
hc_pyconsul/models/__init__.py
hc_pyconsul/models/health.py
hc_pyconsul/models/helpers.py
hc_pyconsul/models/services.py
hc_pyconsul/py.typed
hc_pyconsul-0.3.1.dist-info/METADATA
hc_pyconsul-0.3.1.dist-info/WHEEL
hc_pyconsul-0.3.1.dist-info/LICENSE
hc_pyconsul-0.3.1.dist-info/RECORD
